clirm/__init__.py
clirm/base.py
clirm/py.typed
clirm-0.1.dist-info/WHEEL
clirm-0.1.dist-info/METADATA
clirm-0.1.dist-info/RECORD
