Metadata-Version: 2.1
Name: clirm
Version: 0.1
Summary: Command line-oriented ORM.
Keywords: database,cli,orm
Author-email: Jelle Zijlstra <jelle.zijlstra@gmail.com>
Requires-Python: >=3.11
Classifier: Operating System :: OS Independent
Classifier: Programming Language :: Python
Classifier: Programming Language :: Python :: 3 :: Only
Classifier: Programming Language :: Python :: 3.11
Classifier: Programming Language :: Python :: 3.12
Requires-Dist: typing_extensions
